simplega/__init__.py
simplega/simplega.py
simplega-1.0.2.dist-info/LICENSE
simplega-1.0.2.dist-info/METADATA
simplega-1.0.2.dist-info/WHEEL
simplega-1.0.2.dist-info/top_level.txt
simplega-1.0.2.dist-info/RECORD
