Metadata-Version: 2.1
Name: simplega
Version: 1.0.2
Summary: A simple implementation of Genetic Algorithm
Home-page: https://github.com/nu12/simplega
Author: Alysson A Costa
Author-email: alysson.avila.costa@gmail.com
License: MIT
Platform: UNKNOWN
Classifier: Programming Language :: Python :: 3
Classifier: License :: OSI Approved :: MIT License
Classifier: Operating System :: OS Independent
